ndvector/__init__.py
ndvector/point.py
ndvector/vector.py
ndvector-1.1.0.dist-info/LICENSE
ndvector-1.1.0.dist-info/METADATA
ndvector-1.1.0.dist-info/WHEEL
ndvector-1.1.0.dist-info/top_level.txt
ndvector-1.1.0.dist-info/RECORD
