Metadata-Version: 2.1
Name: ndvector
Version: 1.1.0
Summary: A library for vector math in n dimensions.
Home-page: https://github.com/tkegan/ndvector
Author: Tom Egan
Author-email: tkegan@greenneondesign.com
License: Apache License 2.0
Keywords: vector,math,linear algebra
Platform: UNKNOWN
Classifier: Development Status :: 5 - Production/Stable
Classifier: Intended Audience :: Science/Research
Classifier: License :: OSI Approved :: Apache Software License
Classifier: Operating System :: OS Independent
Classifier: Programming Language :: Python :: 3
Requires-Python: >=3.5
